acspy/__init__.py
acspy/acsc.py
acspy/control.py
acspy/prgs.py
ACSpy-0.0.9.dist-info/LICENSE
ACSpy-0.0.9.dist-info/METADATA
ACSpy-0.0.9.dist-info/WHEEL
ACSpy-0.0.9.dist-info/top_level.txt
ACSpy-0.0.9.dist-info/RECORD
